qiymeti_az/__init__.py
qiymeti_az/company.py
qiymeti_az/scrapper.py
qiymeti_az-0.1.0.dist-info/LICENSE
qiymeti_az-0.1.0.dist-info/METADATA
qiymeti_az-0.1.0.dist-info/WHEEL
qiymeti_az-0.1.0.dist-info/RECORD
